nlinkage/__init__.py
nlinkage/main.py
nlinkage-0.5.dist-info/METADATA
nlinkage-0.5.dist-info/WHEEL
nlinkage-0.5.dist-info/entry_points.txt
nlinkage-0.5.dist-info/top_level.txt
nlinkage-0.5.dist-info/RECORD
